README.txt
setup.py
Products/__init__.py
Products.NewsPage.egg-info/PKG-INFO
Products.NewsPage.egg-info/SOURCES.txt
Products.NewsPage.egg-info/dependency_links.txt
Products.NewsPage.egg-info/entry_points.txt
Products.NewsPage.egg-info/namespace_packages.txt
Products.NewsPage.egg-info/not-zip-safe
Products.NewsPage.egg-info/requires.txt
Products.NewsPage.egg-info/top_level.txt
Products/NewsPage/__init__.py
Products/NewsPage/changes.txt
Products/NewsPage/config.py
Products/NewsPage/configure.zcml
Products/NewsPage/profiles.zcml
Products/NewsPage/readme.txt
Products/NewsPage/refresh.txt
Products/NewsPage/setuphandlers.py
Products/NewsPage/version.txt
Products/NewsPage/content/NewsPage.py
Products/NewsPage/content/__init__.py
Products/NewsPage/content/interfaces.py
Products/NewsPage/i18n/newspage-no.mo
Products/NewsPage/i18n/newspage-no.po
Products/NewsPage/profiles/default/NewsPage_marker.txt
Products/NewsPage/profiles/default/cssregistry.xml
Products/NewsPage/profiles/default/factorytool.xml
Products/NewsPage/profiles/default/import_steps.xml
Products/NewsPage/profiles/default/jsregistry.xml
Products/NewsPage/profiles/default/metadata.xml
Products/NewsPage/profiles/default/skins.xml
Products/NewsPage/profiles/default/types.xml
Products/NewsPage/profiles/default/types/NewsPage.xml
Products/NewsPage/skins/newspage_images/NewsPage.gif
Products/NewsPage/skins/newspage_templates/newspage_macros.pt
Products/NewsPage/skins/newspage_templates/newspage_view.pt