Metadata-Version: 1.0
Name: Products.NewsPage
Version: 1.0.6
Summary: A content type that displays recent news and lets users pin the 3 first stories.
Home-page: http://www.nidelven-it.no/d
Author: Morten W. Petersen
Author-email: info@nidelven-it.no
License: GPL
Keywords: python plone archetypes contenttype presentation
Platform: UNKNOWN
Classifier: Programming Language :: Python
Classifier: Framework :: Plone
